{
    "60151" : {"name" : "name", "id" : "code", "location" : {"lon" : "0.0", "lat" : "0.0"}},
    "51081" : {"name" : "name", "id" : "code", "location" : {"lon" : "0.0", "lat" : "0.0"}},
    "14668" : {"name" : "name", "id" : "code", "location" : {"lon" : "0.0", "lat" : "0.0"}},
    "46591" : {"name" : "name", "id" : "code", "location" : {"lon" : "0.0", "lat" : "0.0"}},
    "47351" : {"name" : "name", "id" : "code", "location" : {"lon" : "0.0", "lat" : "0.0"}},
    "50951" : {"name" : "name", "id" : "code", "location" : {"lon" : "0.0", "lat" : "0.0"}},
    "43131" : {"name" : "name", "id" : "code", "location" : {"lon" : "0.0", "lat" : "0.0"}},
    "46601" : {"name" : "name", "id" : "code", "location" : {"lon" : "0.0", "lat" : "0.0"}},
    "46691" : {"name" : "name", "id" : "code", "location" : {"lon" : "0.0", "lat" : "0.0"}},
    "116683" : {"name" : "name", "id" : "code", "location" : {"lon" : "0.0", "lat" : "0.0"}},
    "47961" : {"name" : "name", "id" : "code", "location" : {"lon" : "0.0", "lat" : "0.0"}},
    "53331" : {"name" : "name", "id" : "code", "location" : {"lon" : "0.0", "lat" : "0.0"}},
    "51071" : {"name" : "name", "id" : "code", "location" : {"lon" : "0.0", "lat" : "0.0"}},
    "14678" : {"name" : "name", "id" : "code", "location" : {"lon" : "0.0", "lat" : "0.0"}},
    "10458" : {"name" : "name", "id" : "code", "location" : {"lon" : "0.0", "lat" : "0.0"}},
    "103373" : {"name" : "name", "id" : "code", "location" : {"lon" : "0.0", "lat" : "0.0"}},
    "116673" : {"name" : "name", "id" : "code", "location" : {"lon" : "0.0", "lat" : "0.0"}},
    "46921" : {"name" : "name", "id" : "code", "location" : {"lon" : "0.0", "lat" : "0.0"}},
    "67623" : {"name" : "name", "id" : "code", "location" : {"lon" : "0.0", "lat" : "0.0"}},
    "8128" : {"name" : "name", "id" : "code", "location" : {"lon" : "0.0", "lat" : "0.0"}},
    "51001" : {"name" : "name", "id" : "code", "location" : {"lon" : "0.0", "lat" : "0.0"}},
    "46891" : {"name" : "name", "id" : "code", "location" : {"lon" : "0.0", "lat" : "0.0"}},
    "50961" : {"name" : "name", "id" : "code", "location" : {"lon" : "0.0", "lat" : "0.0"}},
    "117593" : {"name" : "name", "id" : "code", "location" : {"lon" : "0.0", "lat" : "0.0"}},
    "57511" : {"name" : "name", "id" : "code", "location" : {"lon" : "0.0", "lat" : "0.0"}},
    "44201" : {"name" : "name", "id" : "code", "location" : {"lon" : "0.0", "lat" : "0.0"}},
    "43121" : {"name" : "name", "id" : "code", "location" : {"lon" : "0.0", "lat" : "0.0"}},
    "46541" : {"name" : "name", "id" : "code", "location" : {"lon" : "0.0", "lat" : "0.0"}},
    "14688" : {"name" : "name", "id" : "code", "location" : {"lon" : "0.0", "lat" : "0.0"}},
    "3848" : {"name" : "name", "id" : "code", "location" : {"lon" : "0.0", "lat" : "0.0"}},
    "47911" : {"name" : "name", "id" : "code", "location" : {"lon" : "0.0", "lat" : "0.0"}},
    "14638" : {"name" : "name", "id" : "code", "location" : {"lon" : "0.0", "lat" : "0.0"}},
    "46631" : {"name" : "name", "id" : "code", "location" : {"lon" : "0.0", "lat" : "0.0"}},
    "46561" : {"name" : "name", "id" : "code", "location" : {"lon" : "0.0", "lat" : "0.0"}},
    "47361" : {"name" : "name", "id" : "code", "location" : {"lon" : "0.0", "lat" : "0.0"}},
    "117543" : {"name" : "name", "id" : "code", "location" : {"lon" : "0.0", "lat" : "0.0"}},
    "50891" : {"name" : "name", "id" : "code", "location" : {"lon" : "0.0", "lat" : "0.0"}},
    "14728" : {"name" : "name", "id" : "code", "location" : {"lon" : "0.0", "lat" : "0.0"}},
    "46581" : {"name" : "name", "id" : "code", "location" : {"lon" : "0.0", "lat" : "0.0"}},
    "53421" : {"name" : "name", "id" : "code", "location" : {"lon" : "0.0", "lat" : "0.0"}},
    "116923" : {"name" : "name", "id" : "code", "location" : {"lon" : "0.0", "lat" : "0.0"}},
    "117603" : {"name" : "name", "id" : "code", "location" : {"lon" : "0.0", "lat" : "0.0"}},
    "60141" : {"name" : "name", "id" : "code", "location" : {"lon" : "0.0", "lat" : "0.0"}},
    "60601" : {"name" : "name", "id" : "code", "location" : {"lon" : "0.0", "lat" : "0.0"}},
    "46901" : {"name" : "name", "id" : "code", "location" : {"lon" : "0.0", "lat" : "0.0"}},
    "117883" : {"name" : "name", "id" : "code", "location" : {"lon" : "0.0", "lat" : "0.0"}},
    "67633" : {"name" : "name", "id" : "code", "location" : {"lon" : "0.0", "lat" : "0.0"}},
    "53381" : {"name" : "name", "id" : "code", "location" : {"lon" : "0.0", "lat" : "0.0"}},
    "43141" : {"name" : "name", "id" : "code", "location" : {"lon" : "0.0", "lat" : "0.0"}},
    "50981" : {"name" : "name", "id" : "code", "location" : {"lon" : "0.0", "lat" : "0.0"}},
    "116783" : {"name" : "name", "id" : "code", "location" : {"lon" : "0.0", "lat" : "0.0"}},
    "60131" : {"name" : "name", "id" : "code", "location" : {"lon" : "0.0", "lat" : "0.0"}},
    "14748" : {"name" : "name", "id" : "code", "location" : {"lon" : "0.0", "lat" : "0.0"}},
    "51051" : {"name" : "name", "id" : "code", "location" : {"lon" : "0.0", "lat" : "0.0"}},
    "46641" : {"name" : "name", "id" : "code", "location" : {"lon" : "0.0", "lat" : "0.0"}},
    "46681" : {"name" : "name", "id" : "code", "location" : {"lon" : "0.0", "lat" : "0.0"}},
    "50881" : {"name" : "name", "id" : "code", "location" : {"lon" : "0.0", "lat" : "0.0"}},
    "51061" : {"name" : "name", "id" : "code", "location" : {"lon" : "0.0", "lat" : "0.0"}},
    "47971" : {"name" : "name", "id" : "code", "location" : {"lon" : "0.0", "lat" : "0.0"}},
    "118153" : {"name" : "name", "id" : "code", "location" : {"lon" : "0.0", "lat" : "0.0"}},
    "50871" : {"name" : "name", "id" : "code", "location" : {"lon" : "0.0", "lat" : "0.0"}},
    "50971" : {"name" : "name", "id" : "code", "location" : {"lon" : "0.0", "lat" : "0.0"}}
}