{
    "aberdeen": {"uuid": "4588b4ab-79ea-4c6d-88ae-30b58611f263","code": 60151, "location": {"lat": 57.149717,"lon": -2.094278}},
    "amesbury": {"uuid": "ce39aa68-df35-4462-a239-1edd92241574","code": 51081, "location": {"lat": 51.171759,"lon": -1.761322}},
    "birmingham": {"uuid": "5415b966-f8b8-4b27-8620-1641c1a43e45","code": 14668, "location": {"lat": 52.4829,"lon": -1.8936}},
    "bradford": {"uuid": "97b09a17-671e-4ce2-a62f-dd4a7022f98f","code": 46591, "location": {"lat": 53.795984,"lon": -1.759398}},
    "bridgend": {"uuid": "07097793-72d8-4e93-a4d3-edb896ce185a","code": 47351, "location": {"lat": 51.504286,"lon": -3.576945}},
    "bridgwater": {"uuid": "828520a8-c32e-4f2a-9566-03553ba17e68","code": 50951, "location": {"lat": 51.127889,"lon": -3.003632}},
    "bristol": {"uuid": "8aa5378a-5f22-429c-88f7-2468ffab2757","code": 43131, "location": {"lat": 51.454513,"lon": -2.58791}},
    "cambridge": {"uuid": "3665c7fe-fc24-4b50-9b52-2187944b362c","code": 46601, "location": {"lat": 52.205337,"lon": 0.121817}},
    "cardiff": {"uuid": "f4310851-ef17-4748-b3ba-8ece22f4fdb0","code": 46691, "location": {"lat": 51.481581,"lon": -3.17909}},
    "carlisle": {"uuid": "3fe3a878-30f7-454b-b312-e9cbc4778418","code": 116683, "location": {"lat": 54.892473,"lon": -2.932931}},
    "chester": {"uuid": "04e8553f-09c8-43d0-9ef5-d31a2289eb89","code": 47961, "location": {"lat": 53.193392,"lon": -2.893075}},
    "chesterfield": {"uuid": "2241982a-6c18-4d58-b634-7a278d5492d2","code": 53331, "location": {"lat": 53.235048,"lon": -1.421629}},
    "codford": {"uuid": "4c675425-84fc-412b-a0c3-189a9d134e22","code": 51071, "location": {"lat": 51.157751,"lon": -2.0463802}},
    "coventry": {"uuid": "f45ac44f-1a75-4646-a79d-61386440e317","code": 14678, "location": {"lat": 52.433802,"lon": -1.43304}},
    "dover": {"uuid": "40e30871-8646-11e6-9066-549f350fcb0c","code": 10458, "location": {"lat": 51.128079,"lon": 1.336039}},
    "dundee": {"uuid": "ebe92b4a-799d-4c31-a784-f889046d9cf5","code": 103373, "location": {"lat": 56.462018,"lon": -2.970721}},
    "dunfermline": {"uuid": "efd5d929-528a-4224-95aa-093545545841","code": 116673, "location": {"lat": 56.071741,"lon": -3.452151}},
    "edinburgh": {"uuid": "6f51bf86-01a6-423d-ac31-e35277829e91","code": 46921, "location": {"lat": 55.953252,"lon": -3.188267}},
    "exeter": {"uuid": "37270b23-e4a9-45e3-92a6-06bd94ed417b","code": 67623, "location": {"lat": 50.7260367,"lon": -3.5274889}},
    "folkestone": {"uuid": "40e1c6ae-8646-11e6-9066-549f350fcb0c","code": 8128, "location": {"lat": 51.081397,"lon": 1.169456}},
    "frome": {"uuid": "154a35b8-9c22-41d9-b0a3-7455c4e71d9d","code": 51001, "location": {"lat": 51.230751,"lon": -2.320096}},
    "glasgow": {"uuid": "4a8671ef-0108-4159-8772-5e3b9618b143","code": 46891, "location": {"lat": 55.864237,"lon": -4.251806}},
    "glastonbury": {"uuid": "1fa4086a-566b-420c-a330-a7ed2507bdf7","code": 50961, "location": {"lat": 51.147427,"lon": -2.718454}},
    "hayle": {"uuid": "110a6a55-6a2f-4fc6-8049-97fa18a59223","code": 117593, "location": {"lat": 50.185467,"lon": -5.42091}},
    "heathrow Airport": {"uuid": "9b6a34b8-3ecb-11ea-8017-02437075395e","code": 47891, "location": {"lat": 51.4700223,"lon": -0.4542955}},
    "ilminster": {},
    "lancaster": {"uuid": "e6da4098-043b-44e9-9a1c-6fd0b3dd9dac","code": 44201, "location": {"lat": 54.046575,"lon": -2.8007399}},
    "leeds": {"uuid": "52e0bf1d-25e5-49d0-888e-da8fbc0a25b5","code": 43121, "location": {"lat": 53.8007554,"lon": -1.5490774}},
    "leicester": {"uuid": "d39c1c34-5ba0-467b-93f5-daf35b98ede4","code": 46541, "location": {"lat": 52.6368778,"lon": -1.1397592}},
    "liverpool": {"uuid": "b7e2b915-e36a-4df8-821d-2e5a7ef48889","code": 14688, "location": {"lat": 53.407593,"lon": -2.999149}},
    "london": {"uuid": "40dfdfd8-8646-11e6-9066-549f350fcb0c","code": 3848, "location": {"lat": 51.5073509,"lon": -0.1277583}},
    "london Gatwick Airport": {"uuid": "1a716b56-a361-4946-89a0-34a6424532e9","code": 47911, "location": {"lat": 51.1536621,"lon": -0.1820629}},
    "manchester": {"uuid": "e8aae13c-1801-4553-b103-e10e8500d4e8","code": 14638, "location": {"lat": 53.4807593,"lon": -2.2426305}},
    "middlesbrough": {"uuid": "f265c70c-907f-47c6-8210-35f38e336163","code": 46631, "location": {"lat": 54.574227,"lon": -1.234956}},
    "newcastle Upon Tyne": {"uuid": "88a001c8-eaf6-4126-9ab4-9c0790561e20","code": 46561, "location": {"lat": 54.978252,"lon": -1.61778}},
    "newport (South Wales)": {"uuid": "b143491b-a29f-40c3-aaf0-00cddec2854e","code": 47361, "location": {"lat": 51.584151,"lon": -2.997664}},
    "newquay": {"uuid": "6c851f9e-cb08-4f7e-a0ac-9e83a9990045","code": 117543, "location": {"lat": 50.415497,"lon": -5.073719}},
    "north Petherton": {"uuid": "71c9c87b-f5bc-424d-bc61-54857394948a","code": 50891, "location": {"lat": 51.09205,"lon": -3.018857}},
    "northampton": {"uuid": "dde12416-2886-4022-ae89-20122a7ecb1d","code" : 14728, "location": {"lat": 52.208725,"lon": -0.943391}},
    "nottingham" : {"uuid": "f1d39e6c-8e93-4987-b662-0a962140eae8","code" : 46581, "location": {"lat": 52.9547832,"lon": -1.1581086}},
    "othery" : {"uuid": "0b853e53-d2b6-4841-b9eb-071f43a7707c","code" : 53421, "location": {"lat": 51.0802362,"lon": -2.881248}},
    "penrith" : {"uuid": "86f208e0-96c2-4f75-8f6b-b39722e71b7c","code" : 116923, "location": {"lat": 54.664097,"lon": -2.752708}},
    "penzance" : {"uuid": "c1cfcc76-0766-4a8e-b61d-1b0c064965f9","code" : 117603, "location": {"lat": 50.118798,"lon": -5.537592}},
    "perth" : {"uuid": "0640e5d1-5437-4b69-9357-b758fc840ff9","code" : 60141, "location": {"lat": 56.394994,"lon": -3.4308381}},
    "peterborough" : {"uuid": "836cdfc1-42d7-48eb-a911-51898d7c44e3","code" : 60601, "location": {"lat": 52.5694985,"lon": -0.2405299}},
    "plymouth" : {"uuid": "8e6f0212-5248-441d-8a3f-9bd653fa54c5","code" : 46901, "location": {"lat": 50.3754565,"lon": -4.1426565}},
    "port Talbot" : {"uuid": "1df6cf74-b125-4a31-a9ff-cfb260681076","code" : 117883, "location": {"lat": 51.5946799,"lon": -3.784097}},
    "preston" : {"uuid": "cbd53b99-b2c5-4d67-a576-18a69300d7aa","code" : 67633, "location": {"lat": 53.763201,"lon": -2.70309}},
    "reading" : {"uuid": "9c211de9-c1f3-4ac1-92fa-8913f7b963f4","code" : 53381, "location": {"lat": 51.4542645,"lon": -0.9781303}},
    "sheffield" : {"uuid": "7e720125-5f82-450f-b4cc-ac68935a5b62","code" : 43141, "location": {"lat": 53.381129,"lon": -1.470085}},
    "shepton Mallet" : {"uuid": "15352275-8572-4c3d-90bf-35658fbed483","code" : 50981, "location": {"lat": 51.1909,"lon":-2.547886 }},
    "south Petherton" : {},
    "stevenage" : {"uuid": "965502b3-e883-4b47-9cf6-9e6e7231c9b3","code" : 116783, "location": {"lat": 51.9036812879,"lon": -0.196955273}},
    "stirling" : {"uuid": "dcecb190-0e46-408e-8484-0ce656f52f17","code" : 60131, "location": {"lat": 56.1165227,"lon": -3.9369029}},
    "stoke-on-Trent" : {"uuid": "bb5ef6e6-5b68-4197-8677-383db31c1dc3","code" : 14748, "location": {"lat": 53.002668,"lon": -2.179404}},
    "street": {"uuid": "af7afb9e-b5a2-4938-abb7-d1831c0fe818","code" : 51051, "location": {"lat": 51.124679,"lon": -2.742919}},
    "sunderland" : {"uuid": "b3528d56-c5a5-40da-ab2a-dd834f4e9085","code" : 46641, "location": {"lat": 54.906869,"lon": -1.383801}},
    "swansea" : {"uuid": "1dc7ccd2-5228-40b0-8520-0d86bd764b44","code" : 46681, "location": {"lat": 51.62144,"lon": -3.943646}},
    "taunton" : {"uuid": "012b776f-8b2a-4ff8-bf22-ff2a90f8a049","code" : 50881, "location": {"lat": 51.015344,"lon": -3.106849}},
    "warminster" : {"uuid": "c6a9ff9f-2f67-405c-b58d-ad71287554ab","code" : 51061, "location": {"lat": 51.204629,"lon": -2.181078}},
    "warrington" : {"uuid": "cedf10d6-f803-4a08-87ff-ecdf90eb03f3","code" : 47971, "location": {"lat": 53.3900441,"lon": -2.5969501}},
    "watford" : {"uuid": "79f5346e-d568-486f-94cb-6b38ca6f57ab","code" : 118153, "location": {"lat": 51.6611283,"lon": -0.3970199}},
    "wellington" : {"uuid": "b1f6fefa-7b31-4fc1-99aa-e73380915e21","code" : 50871, "location": {"lat": 50.978564,"lon": -3.2244989}},
    "wells" : {"uuid": "739bb2c4-6287-4a90-b19e-8d80cea41c9e","code" : 50971, "location": {"lat": 51.209347,"lon": -2.6445979}},
    "wincanton" : {}, 
    "yeovil" : {}
  }
  